[
  {
    "date": "2025-09-11",
    "code": "6023",
    "name": "元大期",
    "market": "TPEX",
    "foreign_ratio": 0.0,
    "trust_ratio": 0.0,
    "dealer_ratio": 0.0,
    "three_inst_ratio": 0.0,
    "three_inst_ratio_change_20": 0.0
  },
  {
    "date": "2025-09-12",
    "code": "6023",
    "name": "元大期",
    "market": "TPEX",
    "foreign_ratio": 0.0,
    "trust_ratio": 0.0,
    "dealer_ratio": 0.0,
    "three_inst_ratio": 0.0,
    "three_inst_ratio_change_20": 0.0
  },
  {
    "date": "2025-09-15",
    "code": "6023",
    "name": "元大期",
    "market": "TPEX",
    "foreign_ratio": 0.0,
    "trust_ratio": 0.0003125231579660053,
    "dealer_ratio": 0.0,
    "three_inst_ratio": 0.0003125231579660053,
    "three_inst_ratio_change_20": 0.0
  },
  {
    "date": "2025-09-16",
    "code": "6023",
    "name": "元大期",
    "market": "TPEX",
    "foreign_ratio": 0.0,
    "trust_ratio": 0.0003125231579660053,
    "dealer_ratio": 0.0,
    "three_inst_ratio": 0.0003125231579660053,
    "three_inst_ratio_change_20": 0.0
  },
  {
    "date": "2025-09-17",
    "code": "6023",
    "name": "元大期",
    "market": "TPEX",
    "foreign_ratio": 0.0,
    "trust_ratio": 0.0009375694738980158,
    "dealer_ratio": 0.0,
    "three_inst_ratio": 0.0009375694738980158,
    "three_inst_ratio_change_20": 0.0
  },
  {
    "date": "2025-09-18",
    "code": "6023",
    "name": "元大期",
    "market": "TPEX",
    "foreign_ratio": 0.0,
    "trust_ratio": 0.0009375694738980158,
    "dealer_ratio": 0.0,
    "three_inst_ratio": 0.0009375694738980158,
    "three_inst_ratio_change_20": 0.0
  },
  {
    "date": "2025-09-19",
    "code": "6023",
    "name": "元大期",
    "market": "TPEX",
    "foreign_ratio": 0.0,
    "trust_ratio": 0.0009375694738980158,
    "dealer_ratio": 0.0,
    "three_inst_ratio": 0.0009375694738980158,
    "three_inst_ratio_change_20": 0.0
  },
  {
    "date": "2025-09-22",
    "code": "6023",
    "name": "元大期",
    "market": "TPEX",
    "foreign_ratio": 0.0,
    "trust_ratio": 0.0009375694738980158,
    "dealer_ratio": 0.0,
    "three_inst_ratio": 0.0009375694738980158,
    "three_inst_ratio_change_20": 0.0
  },
  {
    "date": "2025-09-23",
    "code": "6023",
    "name": "元大期",
    "market": "TPEX",
    "foreign_ratio": 0.0,
    "trust_ratio": 0.0009375694738980158,
    "dealer_ratio": 0.0,
    "three_inst_ratio": 0.0009375694738980158,
    "three_inst_ratio_change_20": 0.0
  },
  {
    "date": "2025-09-24",
    "code": "6023",
    "name": "元大期",
    "market": "TPEX",
    "foreign_ratio": 0.0,
    "trust_ratio": 0.0009375694738980158,
    "dealer_ratio": 0.0,
    "three_inst_ratio": 0.0009375694738980158,
    "three_inst_ratio_change_20": 0.0
  },
  {
    "date": "2025-09-25",
    "code": "6023",
    "name": "元大期",
    "market": "TPEX",
    "foreign_ratio": 0.0,
    "trust_ratio": 0.0009375694738980158,
    "dealer_ratio": 0.0,
    "three_inst_ratio": 0.0009375694738980158,
    "three_inst_ratio_change_20": 0.0
  },
  {
    "date": "2025-09-26",
    "code": "6023",
    "name": "元大期",
    "market": "TPEX",
    "foreign_ratio": 0.0,
    "trust_ratio": 0.0009375694738980158,
    "dealer_ratio": 0.0,
    "three_inst_ratio": 0.0009375694738980158,
    "three_inst_ratio_change_20": 0.0
  },
  {
    "date": "2025-09-30",
    "code": "6023",
    "name": "元大期",
    "market": "TPEX",
    "foreign_ratio": 0.0,
    "trust_ratio": 0.0009375694738980158,
    "dealer_ratio": 0.0,
    "three_inst_ratio": 0.0009375694738980158,
    "three_inst_ratio_change_20": 0.0
  },
  {
    "date": "2025-10-01",
    "code": "6023",
    "name": "元大期",
    "market": "TPEX",
    "foreign_ratio": 0.0,
    "trust_ratio": 0.006250463159320106,
    "dealer_ratio": 0.0,
    "three_inst_ratio": 0.006250463159320106,
    "three_inst_ratio_change_20": 0.0
  },
  {
    "date": "2025-10-02",
    "code": "6023",
    "name": "元大期",
    "market": "TPEX",
    "foreign_ratio": 0.0,
    "trust_ratio": 0.011563356844742195,
    "dealer_ratio": 0.0,
    "three_inst_ratio": 0.011563356844742195,
    "three_inst_ratio_change_20": 0.0
  },
  {
    "date": "2025-10-03",
    "code": "6023",
    "name": "元大期",
    "market": "TPEX",
    "foreign_ratio": 0.0,
    "trust_ratio": 0.011563356844742195,
    "dealer_ratio": 0.0,
    "three_inst_ratio": 0.011563356844742195,
    "three_inst_ratio_change_20": 0.0
  },
  {
    "date": "2025-10-07",
    "code": "6023",
    "name": "元大期",
    "market": "TPEX",
    "foreign_ratio": 0.0,
    "trust_ratio": 0.011563356844742195,
    "dealer_ratio": 0.0,
    "three_inst_ratio": 0.011563356844742195,
    "three_inst_ratio_change_20": 0.0
  },
  {
    "date": "2025-10-08",
    "code": "6023",
    "name": "元大期",
    "market": "TPEX",
    "foreign_ratio": 0.0,
    "trust_ratio": 0.013751018950504233,
    "dealer_ratio": 0.0,
    "three_inst_ratio": 0.013751018950504233,
    "three_inst_ratio_change_20": 0.0
  },
  {
    "date": "2025-10-09",
    "code": "6023",
    "name": "元大期",
    "market": "TPEX",
    "foreign_ratio": 0.0,
    "trust_ratio": 0.014376065266436243,
    "dealer_ratio": 0.0,
    "three_inst_ratio": 0.014376065266436243,
    "three_inst_ratio_change_20": 0.0
  },
  {
    "date": "2025-10-13",
    "code": "6023",
    "name": "元大期",
    "market": "TPEX",
    "foreign_ratio": 0.0,
    "trust_ratio": 0.016251204214232276,
    "dealer_ratio": 0.0,
    "three_inst_ratio": 0.016251204214232276,
    "three_inst_ratio_change_20": 0.0
  },
  {
    "date": "2025-10-14",
    "code": "6023",
    "name": "元大期",
    "market": "TPEX",
    "foreign_ratio": 0.0,
    "trust_ratio": 0.01906391263592632,
    "dealer_ratio": 0.0,
    "three_inst_ratio": 0.01906391263592632,
    "three_inst_ratio_change_20": 0.01906391263592632
  },
  {
    "date": "2025-10-15",
    "code": "6023",
    "name": "元大期",
    "market": "TPEX",
    "foreign_ratio": 0.0,
    "trust_ratio": 0.02187662105762037,
    "dealer_ratio": 0.0,
    "three_inst_ratio": 0.02187662105762037,
    "three_inst_ratio_change_20": 0.02187662105762037
  },
  {
    "date": "2025-10-16",
    "code": "6023",
    "name": "元大期",
    "market": "TPEX",
    "foreign_ratio": 0.0,
    "trust_ratio": 0.022189144215586376,
    "dealer_ratio": 0.0,
    "three_inst_ratio": 0.022189144215586376,
    "three_inst_ratio_change_20": 0.02187662105762037
  },
  {
    "date": "2025-10-17",
    "code": "6023",
    "name": "元大期",
    "market": "TPEX",
    "foreign_ratio": 0.0,
    "trust_ratio": 0.02312671368948439,
    "dealer_ratio": 0.0,
    "three_inst_ratio": 0.02312671368948439,
    "three_inst_ratio_change_20": 0.022814190531518383
  },
  {
    "date": "2025-10-20",
    "code": "6023",
    "name": "元大期",
    "market": "TPEX",
    "foreign_ratio": 0.0,
    "trust_ratio": 0.023439236847450397,
    "dealer_ratio": 0.0,
    "three_inst_ratio": 0.023439236847450397,
    "three_inst_ratio_change_20": 0.02250166737355238
  },
  {
    "date": "2025-10-21",
    "code": "6023",
    "name": "元大期",
    "market": "TPEX",
    "foreign_ratio": 0.0,
    "trust_ratio": 0.023439236847450397,
    "dealer_ratio": 0.0,
    "three_inst_ratio": 0.023439236847450397,
    "three_inst_ratio_change_20": 0.02250166737355238
  },
  {
    "date": "2025-10-22",
    "code": "6023",
    "name": "元大期",
    "market": "TPEX",
    "foreign_ratio": 0.0,
    "trust_ratio": 0.023439236847450397,
    "dealer_ratio": 0.0,
    "three_inst_ratio": 0.023439236847450397,
    "three_inst_ratio_change_20": 0.02250166737355238
  },
  {
    "date": "2025-10-23",
    "code": "6023",
    "name": "元大期",
    "market": "TPEX",
    "foreign_ratio": 0.0,
    "trust_ratio": 0.023439236847450397,
    "dealer_ratio": 0.0,
    "three_inst_ratio": 0.023439236847450397,
    "three_inst_ratio_change_20": 0.02250166737355238
  },
  {
    "date": "2025-10-27",
    "code": "6023",
    "name": "元大期",
    "market": "TPEX",
    "foreign_ratio": 0.0,
    "trust_ratio": 0.023439236847450397,
    "dealer_ratio": 0.0,
    "three_inst_ratio": 0.023439236847450397,
    "three_inst_ratio_change_20": 0.02250166737355238
  },
  {
    "date": "2025-10-28",
    "code": "6023",
    "name": "元大期",
    "market": "TPEX",
    "foreign_ratio": 0.0,
    "trust_ratio": 0.023439236847450397,
    "dealer_ratio": 0.0,
    "three_inst_ratio": 0.023439236847450397,
    "three_inst_ratio_change_20": 0.02250166737355238
  },
  {
    "date": "2025-10-29",
    "code": "6023",
    "name": "元大期",
    "market": "TPEX",
    "foreign_ratio": 0.0,
    "trust_ratio": 0.023439236847450397,
    "dealer_ratio": 0.0,
    "three_inst_ratio": 0.023439236847450397,
    "three_inst_ratio_change_20": 0.02250166737355238
  },
  {
    "date": "2025-10-30",
    "code": "6023",
    "name": "元大期",
    "market": "TPEX",
    "foreign_ratio": 0.0,
    "trust_ratio": 0.023439236847450397,
    "dealer_ratio": 0.0,
    "three_inst_ratio": 0.023439236847450397,
    "three_inst_ratio_change_20": 0.02250166737355238
  },
  {
    "date": "2025-10-31",
    "code": "6023",
    "name": "元大期",
    "market": "TPEX",
    "foreign_ratio": 0.0,
    "trust_ratio": 0.023439236847450397,
    "dealer_ratio": 0.0,
    "three_inst_ratio": 0.023439236847450397,
    "three_inst_ratio_change_20": 0.02250166737355238
  },
  {
    "date": "2025-11-03",
    "code": "6023",
    "name": "元大期",
    "market": "TPEX",
    "foreign_ratio": 0.0,
    "trust_ratio": 0.02593942211117844,
    "dealer_ratio": 0.0,
    "three_inst_ratio": 0.02593942211117844,
    "three_inst_ratio_change_20": 0.019688958951858335
  },
  {
    "date": "2025-11-04",
    "code": "6023",
    "name": "元大期",
    "market": "TPEX",
    "foreign_ratio": 0.0,
    "trust_ratio": 0.028439607374906483,
    "dealer_ratio": 0.0,
    "three_inst_ratio": 0.028439607374906483,
    "three_inst_ratio_change_20": 0.01687625053016429
  },
  {
    "date": "2025-11-05",
    "code": "6023",
    "name": "元大期",
    "market": "TPEX",
    "foreign_ratio": 0.0,
    "trust_ratio": 0.028439607374906483,
    "dealer_ratio": 0.0,
    "three_inst_ratio": 0.028439607374906483,
    "three_inst_ratio_change_20": 0.01687625053016429
  },
  {
    "date": "2025-11-06",
    "code": "6023",
    "name": "元大期",
    "market": "TPEX",
    "foreign_ratio": 0.0,
    "trust_ratio": 0.028439607374906483,
    "dealer_ratio": 0.0,
    "three_inst_ratio": 0.028439607374906483,
    "three_inst_ratio_change_20": 0.01687625053016429
  },
  {
    "date": "2025-11-07",
    "code": "6023",
    "name": "元大期",
    "market": "TPEX",
    "foreign_ratio": 0.0,
    "trust_ratio": 0.028439607374906483,
    "dealer_ratio": 0.0,
    "three_inst_ratio": 0.028439607374906483,
    "three_inst_ratio_change_20": 0.01468858842440225
  },
  {
    "date": "2025-11-10",
    "code": "6023",
    "name": "元大期",
    "market": "TPEX",
    "foreign_ratio": 0.0,
    "trust_ratio": 0.028439607374906483,
    "dealer_ratio": 0.0,
    "three_inst_ratio": 0.028439607374906483,
    "three_inst_ratio_change_20": 0.01406354210847024
  },
  {
    "date": "2025-11-11",
    "code": "6023",
    "name": "元大期",
    "market": "TPEX",
    "foreign_ratio": 0.0,
    "trust_ratio": 0.028127084216940476,
    "dealer_ratio": 0.0,
    "three_inst_ratio": 0.028127084216940476,
    "three_inst_ratio_change_20": 0.0118758800027082
  },
  {
    "date": "2025-11-12",
    "code": "6023",
    "name": "元大期",
    "market": "TPEX",
    "foreign_ratio": 0.0,
    "trust_ratio": 0.027814561058974473,
    "dealer_ratio": 0.0,
    "three_inst_ratio": 0.027814561058974473,
    "three_inst_ratio_change_20": 0.008750648423048152
  },
  {
    "date": "2025-11-13",
    "code": "6023",
    "name": "元大期",
    "market": "TPEX",
    "foreign_ratio": 0.0,
    "trust_ratio": 0.027502037901008466,
    "dealer_ratio": 0.0,
    "three_inst_ratio": 0.027502037901008466,
    "three_inst_ratio_change_20": 0.005625416843388097
  },
  {
    "date": "2025-11-14",
    "code": "6023",
    "name": "元大期",
    "market": "TPEX",
    "foreign_ratio": 0.0,
    "trust_ratio": 0.027502037901008466,
    "dealer_ratio": 0.0,
    "three_inst_ratio": 0.027502037901008466,
    "three_inst_ratio_change_20": 0.00531289368542209
  },
  {
    "date": "2025-11-17",
    "code": "6023",
    "name": "元大期",
    "market": "TPEX",
    "foreign_ratio": 0.0,
    "trust_ratio": 0.027502037901008466,
    "dealer_ratio": 0.0,
    "three_inst_ratio": 0.027502037901008466,
    "three_inst_ratio_change_20": 0.004375324211524076
  },
  {
    "date": "2025-11-18",
    "code": "6023",
    "name": "元大期",
    "market": "TPEX",
    "foreign_ratio": 0.0,
    "trust_ratio": 0.027502037901008466,
    "dealer_ratio": 0.0,
    "three_inst_ratio": 0.027502037901008466,
    "three_inst_ratio_change_20": 0.004062801053558069
  },
  {
    "date": "2025-11-19",
    "code": "6023",
    "name": "元大期",
    "market": "TPEX",
    "foreign_ratio": 0.0,
    "trust_ratio": 0.027814561058974473,
    "dealer_ratio": 0.0,
    "three_inst_ratio": 0.027814561058974473,
    "three_inst_ratio_change_20": 0.004375324211524076
  },
  {
    "date": "2025-11-20",
    "code": "6023",
    "name": "元大期",
    "market": "TPEX",
    "foreign_ratio": 0.0,
    "trust_ratio": 0.027814561058974473,
    "dealer_ratio": 0.0,
    "three_inst_ratio": 0.027814561058974473,
    "three_inst_ratio_change_20": 0.004375324211524076
  },
  {
    "date": "2025-11-21",
    "code": "6023",
    "name": "元大期",
    "market": "TPEX",
    "foreign_ratio": 0.0,
    "trust_ratio": 0.027814561058974473,
    "dealer_ratio": 0.0,
    "three_inst_ratio": 0.027814561058974473,
    "three_inst_ratio_change_20": 0.004375324211524076
  },
  {
    "date": "2025-11-24",
    "code": "6023",
    "name": "元大期",
    "market": "TPEX",
    "foreign_ratio": 0.0,
    "trust_ratio": 0.027814561058974473,
    "dealer_ratio": 0.0,
    "three_inst_ratio": 0.027814561058974473,
    "three_inst_ratio_change_20": 0.004375324211524076
  },
  {
    "date": "2025-11-25",
    "code": "6023",
    "name": "元大期",
    "market": "TPEX",
    "foreign_ratio": 0.0,
    "trust_ratio": 0.027814561058974473,
    "dealer_ratio": 0.0,
    "three_inst_ratio": 0.027814561058974473,
    "three_inst_ratio_change_20": 0.004375324211524076
  },
  {
    "date": "2025-11-26",
    "code": "6023",
    "name": "元大期",
    "market": "TPEX",
    "foreign_ratio": 0.0,
    "trust_ratio": 0.027814561058974473,
    "dealer_ratio": 0.0,
    "three_inst_ratio": 0.027814561058974473,
    "three_inst_ratio_change_20": 0.004375324211524076
  },
  {
    "date": "2025-11-27",
    "code": "6023",
    "name": "元大期",
    "market": "TPEX",
    "foreign_ratio": 0.0,
    "trust_ratio": 0.027814561058974473,
    "dealer_ratio": 0.0,
    "three_inst_ratio": 0.027814561058974473,
    "three_inst_ratio_change_20": 0.004375324211524076
  },
  {
    "date": "2025-11-28",
    "code": "6023",
    "name": "元大期",
    "market": "TPEX",
    "foreign_ratio": 0.0,
    "trust_ratio": 0.027814561058974473,
    "dealer_ratio": 0.0,
    "three_inst_ratio": 0.027814561058974473,
    "three_inst_ratio_change_20": 0.004375324211524076
  },
  {
    "date": "2025-12-01",
    "code": "6023",
    "name": "元大期",
    "market": "TPEX",
    "foreign_ratio": 0.0,
    "trust_ratio": 0.028127084216940476,
    "dealer_ratio": 0.0,
    "three_inst_ratio": 0.028127084216940476,
    "three_inst_ratio_change_20": 0.0021876621057620345
  },
  {
    "date": "2025-12-02",
    "code": "6023",
    "name": "元大期",
    "market": "TPEX",
    "foreign_ratio": 0.0,
    "trust_ratio": 0.028127084216940476,
    "dealer_ratio": 0.0,
    "three_inst_ratio": 0.028127084216940476,
    "three_inst_ratio_change_20": -0.0003125231579660069
  },
  {
    "date": "2025-12-03",
    "code": "6023",
    "name": "元大期",
    "market": "TPEX",
    "foreign_ratio": 0.0,
    "trust_ratio": 0.028127084216940476,
    "dealer_ratio": 0.0,
    "three_inst_ratio": 0.028127084216940476,
    "three_inst_ratio_change_20": -0.0003125231579660069
  },
  {
    "date": "2025-12-04",
    "code": "6023",
    "name": "元大期",
    "market": "TPEX",
    "foreign_ratio": 0.0,
    "trust_ratio": 0.028127084216940476,
    "dealer_ratio": 0.0,
    "three_inst_ratio": 0.028127084216940476,
    "three_inst_ratio_change_20": -0.0003125231579660069
  },
  {
    "date": "2025-12-05",
    "code": "6023",
    "name": "元大期",
    "market": "TPEX",
    "foreign_ratio": 0.0,
    "trust_ratio": 0.028127084216940476,
    "dealer_ratio": 0.0,
    "three_inst_ratio": 0.028127084216940476,
    "three_inst_ratio_change_20": -0.0003125231579660069
  },
  {
    "date": "2025-12-08",
    "code": "6023",
    "name": "元大期",
    "market": "TPEX",
    "foreign_ratio": 0.0,
    "trust_ratio": 0.028127084216940476,
    "dealer_ratio": 0.0,
    "three_inst_ratio": 0.028127084216940476,
    "three_inst_ratio_change_20": -0.0003125231579660069
  },
  {
    "date": "2025-12-09",
    "code": "6023",
    "name": "元大期",
    "market": "TPEX",
    "foreign_ratio": 0.0,
    "trust_ratio": 0.027814561058974473,
    "dealer_ratio": 0.0,
    "three_inst_ratio": 0.027814561058974473,
    "three_inst_ratio_change_20": -0.00031252315796600344
  },
  {
    "date": "2025-12-10",
    "code": "6023",
    "name": "元大期",
    "market": "TPEX",
    "foreign_ratio": 0.0,
    "trust_ratio": 0.026251945269144445,
    "dealer_ratio": 0.0,
    "three_inst_ratio": 0.026251945269144445,
    "three_inst_ratio_change_20": -0.0015626157898300276
  },
  {
    "date": "2025-12-11",
    "code": "6023",
    "name": "元大期",
    "market": "TPEX",
    "foreign_ratio": 0.0,
    "trust_ratio": 0.026251945269144445,
    "dealer_ratio": 0.0,
    "three_inst_ratio": 0.026251945269144445,
    "three_inst_ratio_change_20": -0.0012500926318640207
  },
  {
    "date": "2025-12-12",
    "code": "6023",
    "name": "元大期",
    "market": "TPEX",
    "foreign_ratio": 0.0,
    "trust_ratio": 0.026251945269144445,
    "dealer_ratio": 0.0,
    "three_inst_ratio": 0.026251945269144445,
    "three_inst_ratio_change_20": -0.0012500926318640207
  }
]