[
  {
    "date": "2025-09-11",
    "code": "6187",
    "name": "萬潤",
    "market": "TPEX",
    "foreign_ratio": 0.0,
    "trust_ratio": 0.37984228597345143,
    "dealer_ratio": 0.0,
    "three_inst_ratio": 0.37984228597345143,
    "three_inst_ratio_change_20": 0.0
  },
  {
    "date": "2025-09-12",
    "code": "6187",
    "name": "萬潤",
    "market": "TPEX",
    "foreign_ratio": 0.0,
    "trust_ratio": 0.902125429186947,
    "dealer_ratio": 0.0,
    "three_inst_ratio": 0.902125429186947,
    "three_inst_ratio_change_20": 0.0
  },
  {
    "date": "2025-09-15",
    "code": "6187",
    "name": "萬潤",
    "market": "TPEX",
    "foreign_ratio": 0.0,
    "trust_ratio": 1.1003040131730957,
    "dealer_ratio": 0.0,
    "three_inst_ratio": 1.1003040131730957,
    "three_inst_ratio_change_20": 0.0
  },
  {
    "date": "2025-09-16",
    "code": "6187",
    "name": "萬潤",
    "market": "TPEX",
    "foreign_ratio": 0.0,
    "trust_ratio": 1.1003040131730957,
    "dealer_ratio": 0.0,
    "three_inst_ratio": 1.1003040131730957,
    "three_inst_ratio_change_20": 0.0
  },
  {
    "date": "2025-09-17",
    "code": "6187",
    "name": "萬潤",
    "market": "TPEX",
    "foreign_ratio": 0.0,
    "trust_ratio": 1.1013361932980235,
    "dealer_ratio": 0.0,
    "three_inst_ratio": 1.1013361932980235,
    "three_inst_ratio_change_20": 0.0
  },
  {
    "date": "2025-09-18",
    "code": "6187",
    "name": "萬潤",
    "market": "TPEX",
    "foreign_ratio": 0.0,
    "trust_ratio": 1.3366732617815749,
    "dealer_ratio": 0.0,
    "three_inst_ratio": 1.3366732617815749,
    "three_inst_ratio_change_20": 0.0
  },
  {
    "date": "2025-09-19",
    "code": "6187",
    "name": "萬潤",
    "market": "TPEX",
    "foreign_ratio": 0.0,
    "trust_ratio": 1.3982015190285244,
    "dealer_ratio": 0.0,
    "three_inst_ratio": 1.3982015190285244,
    "three_inst_ratio_change_20": 0.0
  },
  {
    "date": "2025-09-22",
    "code": "6187",
    "name": "萬潤",
    "market": "TPEX",
    "foreign_ratio": 0.0,
    "trust_ratio": 1.3992336991534524,
    "dealer_ratio": 0.0,
    "three_inst_ratio": 1.3992336991534524,
    "three_inst_ratio_change_20": 0.0
  },
  {
    "date": "2025-09-23",
    "code": "6187",
    "name": "萬潤",
    "market": "TPEX",
    "foreign_ratio": 0.0,
    "trust_ratio": 1.5261918545195787,
    "dealer_ratio": 0.0,
    "three_inst_ratio": 1.5261918545195787,
    "three_inst_ratio_change_20": 0.0
  },
  {
    "date": "2025-09-24",
    "code": "6187",
    "name": "萬潤",
    "market": "TPEX",
    "foreign_ratio": 0.0,
    "trust_ratio": 1.7202417180060159,
    "dealer_ratio": 0.0,
    "three_inst_ratio": 1.7202417180060159,
    "three_inst_ratio_change_20": 0.0
  },
  {
    "date": "2025-09-25",
    "code": "6187",
    "name": "萬潤",
    "market": "TPEX",
    "foreign_ratio": 0.0,
    "trust_ratio": 1.7223060782558715,
    "dealer_ratio": 0.0,
    "three_inst_ratio": 1.7223060782558715,
    "three_inst_ratio_change_20": 0.0
  },
  {
    "date": "2025-09-26",
    "code": "6187",
    "name": "萬潤",
    "market": "TPEX",
    "foreign_ratio": 0.0,
    "trust_ratio": 1.7223060782558715,
    "dealer_ratio": 0.0,
    "three_inst_ratio": 1.7223060782558715,
    "three_inst_ratio_change_20": 0.0
  },
  {
    "date": "2025-09-30",
    "code": "6187",
    "name": "萬潤",
    "market": "TPEX",
    "foreign_ratio": 0.0,
    "trust_ratio": 1.7223060782558715,
    "dealer_ratio": 0.0,
    "three_inst_ratio": 1.7223060782558715,
    "three_inst_ratio_change_20": 0.0
  },
  {
    "date": "2025-10-01",
    "code": "6187",
    "name": "萬潤",
    "market": "TPEX",
    "foreign_ratio": 0.0,
    "trust_ratio": 1.7223060782558715,
    "dealer_ratio": 0.0,
    "three_inst_ratio": 1.7223060782558715,
    "three_inst_ratio_change_20": 0.0
  },
  {
    "date": "2025-10-02",
    "code": "6187",
    "name": "萬潤",
    "market": "TPEX",
    "foreign_ratio": 0.0,
    "trust_ratio": 1.7223060782558715,
    "dealer_ratio": 0.0,
    "three_inst_ratio": 1.7223060782558715,
    "three_inst_ratio_change_20": 0.0
  },
  {
    "date": "2025-10-03",
    "code": "6187",
    "name": "萬潤",
    "market": "TPEX",
    "foreign_ratio": 0.0,
    "trust_ratio": 1.8306849913732965,
    "dealer_ratio": 0.0,
    "three_inst_ratio": 1.8306849913732965,
    "three_inst_ratio_change_20": 0.0
  },
  {
    "date": "2025-10-07",
    "code": "6187",
    "name": "萬潤",
    "market": "TPEX",
    "foreign_ratio": 0.0,
    "trust_ratio": 1.8306849913732965,
    "dealer_ratio": 0.0,
    "three_inst_ratio": 1.8306849913732965,
    "three_inst_ratio_change_20": 0.0
  },
  {
    "date": "2025-10-08",
    "code": "6187",
    "name": "萬潤",
    "market": "TPEX",
    "foreign_ratio": 0.0,
    "trust_ratio": 1.8317171714982243,
    "dealer_ratio": 0.0,
    "three_inst_ratio": 1.8317171714982243,
    "three_inst_ratio_change_20": 0.0
  },
  {
    "date": "2025-10-09",
    "code": "6187",
    "name": "萬潤",
    "market": "TPEX",
    "foreign_ratio": 0.0,
    "trust_ratio": 2.0587967989823532,
    "dealer_ratio": 0.0,
    "three_inst_ratio": 2.0587967989823532,
    "three_inst_ratio_change_20": 0.0
  },
  {
    "date": "2025-10-13",
    "code": "6187",
    "name": "萬潤",
    "market": "TPEX",
    "foreign_ratio": 0.0,
    "trust_ratio": 2.0587967989823532,
    "dealer_ratio": 0.0,
    "three_inst_ratio": 2.0587967989823532,
    "three_inst_ratio_change_20": 0.0
  },
  {
    "date": "2025-10-14",
    "code": "6187",
    "name": "萬潤",
    "market": "TPEX",
    "foreign_ratio": 0.0,
    "trust_ratio": 2.0600354151322664,
    "dealer_ratio": 0.0,
    "three_inst_ratio": 2.0600354151322664,
    "three_inst_ratio_change_20": 1.680193129158815
  },
  {
    "date": "2025-10-15",
    "code": "6187",
    "name": "萬潤",
    "market": "TPEX",
    "foreign_ratio": 0.0,
    "trust_ratio": 2.0602418511572522,
    "dealer_ratio": 0.0,
    "three_inst_ratio": 2.0602418511572522,
    "three_inst_ratio_change_20": 1.158116421970305
  },
  {
    "date": "2025-10-16",
    "code": "6187",
    "name": "萬潤",
    "market": "TPEX",
    "foreign_ratio": 0.0,
    "trust_ratio": 2.0602418511572522,
    "dealer_ratio": 0.0,
    "three_inst_ratio": 2.0602418511572522,
    "three_inst_ratio_change_20": 0.9599378379841566
  },
  {
    "date": "2025-10-17",
    "code": "6187",
    "name": "萬潤",
    "market": "TPEX",
    "foreign_ratio": 0.0,
    "trust_ratio": 2.109280728892575,
    "dealer_ratio": 0.0,
    "three_inst_ratio": 2.109280728892575,
    "three_inst_ratio_change_20": 1.0089767157194791
  },
  {
    "date": "2025-10-20",
    "code": "6187",
    "name": "萬潤",
    "market": "TPEX",
    "foreign_ratio": 0.0,
    "trust_ratio": 2.109641991936299,
    "dealer_ratio": 0.0,
    "three_inst_ratio": 2.109641991936299,
    "three_inst_ratio_change_20": 1.0083057986382757
  },
  {
    "date": "2025-10-21",
    "code": "6187",
    "name": "萬潤",
    "market": "TPEX",
    "foreign_ratio": 0.0,
    "trust_ratio": 2.110674172061227,
    "dealer_ratio": 0.0,
    "three_inst_ratio": 2.110674172061227,
    "three_inst_ratio_change_20": 0.7740009102796521
  },
  {
    "date": "2025-10-22",
    "code": "6187",
    "name": "萬潤",
    "market": "TPEX",
    "foreign_ratio": 0.0,
    "trust_ratio": 2.110880608086213,
    "dealer_ratio": 0.0,
    "three_inst_ratio": 2.110880608086213,
    "three_inst_ratio_change_20": 0.7126790890576884
  },
  {
    "date": "2025-10-23",
    "code": "6187",
    "name": "萬潤",
    "market": "TPEX",
    "foreign_ratio": 0.0,
    "trust_ratio": 2.110880608086213,
    "dealer_ratio": 0.0,
    "three_inst_ratio": 2.110880608086213,
    "three_inst_ratio_change_20": 0.7116469089327604
  },
  {
    "date": "2025-10-27",
    "code": "6187",
    "name": "萬潤",
    "market": "TPEX",
    "foreign_ratio": 0.0,
    "trust_ratio": 2.1426717559339905,
    "dealer_ratio": 0.0,
    "three_inst_ratio": 2.1426717559339905,
    "three_inst_ratio_change_20": 0.6164799014144118
  },
  {
    "date": "2025-10-28",
    "code": "6187",
    "name": "萬潤",
    "market": "TPEX",
    "foreign_ratio": 0.0,
    "trust_ratio": 2.305756215672592,
    "dealer_ratio": 0.0,
    "three_inst_ratio": 2.305756215672592,
    "three_inst_ratio_change_20": 0.585514497666576
  },
  {
    "date": "2025-10-29",
    "code": "6187",
    "name": "萬潤",
    "market": "TPEX",
    "foreign_ratio": 0.0,
    "trust_ratio": 2.305756215672592,
    "dealer_ratio": 0.0,
    "three_inst_ratio": 2.305756215672592,
    "three_inst_ratio_change_20": 0.5834501374167205
  },
  {
    "date": "2025-10-30",
    "code": "6187",
    "name": "萬潤",
    "market": "TPEX",
    "foreign_ratio": 0.0,
    "trust_ratio": 2.305756215672592,
    "dealer_ratio": 0.0,
    "three_inst_ratio": 2.305756215672592,
    "three_inst_ratio_change_20": 0.5834501374167205
  },
  {
    "date": "2025-10-31",
    "code": "6187",
    "name": "萬潤",
    "market": "TPEX",
    "foreign_ratio": 0.0,
    "trust_ratio": 2.609217172401382,
    "dealer_ratio": 0.0,
    "three_inst_ratio": 2.609217172401382,
    "three_inst_ratio_change_20": 0.8869110941455107
  },
  {
    "date": "2025-11-03",
    "code": "6187",
    "name": "萬潤",
    "market": "TPEX",
    "foreign_ratio": 0.0,
    "trust_ratio": 2.609733262463846,
    "dealer_ratio": 0.0,
    "three_inst_ratio": 2.609733262463846,
    "three_inst_ratio_change_20": 0.8874271842079746
  },
  {
    "date": "2025-11-04",
    "code": "6187",
    "name": "萬潤",
    "market": "TPEX",
    "foreign_ratio": 0.0,
    "trust_ratio": 2.609733262463846,
    "dealer_ratio": 0.0,
    "three_inst_ratio": 2.609733262463846,
    "three_inst_ratio_change_20": 0.8874271842079746
  },
  {
    "date": "2025-11-05",
    "code": "6187",
    "name": "萬潤",
    "market": "TPEX",
    "foreign_ratio": 0.0,
    "trust_ratio": 2.6100429165013246,
    "dealer_ratio": 0.0,
    "three_inst_ratio": 2.6100429165013246,
    "three_inst_ratio_change_20": 0.779357925128028
  },
  {
    "date": "2025-11-06",
    "code": "6187",
    "name": "萬潤",
    "market": "TPEX",
    "foreign_ratio": 0.0,
    "trust_ratio": 2.6100429165013246,
    "dealer_ratio": 0.0,
    "three_inst_ratio": 2.6100429165013246,
    "three_inst_ratio_change_20": 0.779357925128028
  },
  {
    "date": "2025-11-07",
    "code": "6187",
    "name": "萬潤",
    "market": "TPEX",
    "foreign_ratio": 0.0,
    "trust_ratio": 2.615203817125964,
    "dealer_ratio": 0.0,
    "three_inst_ratio": 2.615203817125964,
    "three_inst_ratio_change_20": 0.7834866456277396
  },
  {
    "date": "2025-11-10",
    "code": "6187",
    "name": "萬潤",
    "market": "TPEX",
    "foreign_ratio": 0.0,
    "trust_ratio": 2.615203817125964,
    "dealer_ratio": 0.0,
    "three_inst_ratio": 2.615203817125964,
    "three_inst_ratio_change_20": 0.5564070181436107
  },
  {
    "date": "2025-11-11",
    "code": "6187",
    "name": "萬潤",
    "market": "TPEX",
    "foreign_ratio": 0.0,
    "trust_ratio": 2.615203817125964,
    "dealer_ratio": 0.0,
    "three_inst_ratio": 2.615203817125964,
    "three_inst_ratio_change_20": 0.5564070181436107
  },
  {
    "date": "2025-11-12",
    "code": "6187",
    "name": "萬潤",
    "market": "TPEX",
    "foreign_ratio": 0.0,
    "trust_ratio": 2.615203817125964,
    "dealer_ratio": 0.0,
    "three_inst_ratio": 2.615203817125964,
    "three_inst_ratio_change_20": 0.5551684019936975
  },
  {
    "date": "2025-11-13",
    "code": "6187",
    "name": "萬潤",
    "market": "TPEX",
    "foreign_ratio": 0.0,
    "trust_ratio": 2.615203817125964,
    "dealer_ratio": 0.0,
    "three_inst_ratio": 2.615203817125964,
    "three_inst_ratio_change_20": 0.5549619659687117
  },
  {
    "date": "2025-11-14",
    "code": "6187",
    "name": "萬潤",
    "market": "TPEX",
    "foreign_ratio": 0.0,
    "trust_ratio": 2.615203817125964,
    "dealer_ratio": 0.0,
    "three_inst_ratio": 2.615203817125964,
    "three_inst_ratio_change_20": 0.5549619659687117
  },
  {
    "date": "2025-11-17",
    "code": "6187",
    "name": "萬潤",
    "market": "TPEX",
    "foreign_ratio": 0.0,
    "trust_ratio": 2.561530450629715,
    "dealer_ratio": 0.0,
    "three_inst_ratio": 2.561530450629715,
    "three_inst_ratio_change_20": 0.4522497217371404
  },
  {
    "date": "2025-11-18",
    "code": "6187",
    "name": "萬潤",
    "market": "TPEX",
    "foreign_ratio": 0.0,
    "trust_ratio": 2.5656591711294268,
    "dealer_ratio": 0.0,
    "three_inst_ratio": 2.5656591711294268,
    "three_inst_ratio_change_20": 0.45601717919312756
  },
  {
    "date": "2025-11-19",
    "code": "6187",
    "name": "萬潤",
    "market": "TPEX",
    "foreign_ratio": 0.0,
    "trust_ratio": 2.632750879249737,
    "dealer_ratio": 0.0,
    "three_inst_ratio": 2.632750879249737,
    "three_inst_ratio_change_20": 0.5220767071885102
  },
  {
    "date": "2025-11-20",
    "code": "6187",
    "name": "萬潤",
    "market": "TPEX",
    "foreign_ratio": 0.0,
    "trust_ratio": 2.6302065552417897,
    "dealer_ratio": 0.0,
    "three_inst_ratio": 2.6302065552417897,
    "three_inst_ratio_change_20": 0.5193259471555769
  },
  {
    "date": "2025-11-21",
    "code": "6187",
    "name": "萬潤",
    "market": "TPEX",
    "foreign_ratio": 0.0,
    "trust_ratio": 2.6281421949919346,
    "dealer_ratio": 0.0,
    "three_inst_ratio": 2.6281421949919346,
    "three_inst_ratio_change_20": 0.5172615869057218
  },
  {
    "date": "2025-11-24",
    "code": "6187",
    "name": "萬潤",
    "market": "TPEX",
    "foreign_ratio": 0.0,
    "trust_ratio": 2.629174375116862,
    "dealer_ratio": 0.0,
    "three_inst_ratio": 2.629174375116862,
    "three_inst_ratio_change_20": 0.4865026191828714
  },
  {
    "date": "2025-11-25",
    "code": "6187",
    "name": "萬潤",
    "market": "TPEX",
    "foreign_ratio": 0.0,
    "trust_ratio": 2.629174375116862,
    "dealer_ratio": 0.0,
    "three_inst_ratio": 2.629174375116862,
    "three_inst_ratio_change_20": 0.32341815944427
  },
  {
    "date": "2025-11-26",
    "code": "6187",
    "name": "萬潤",
    "market": "TPEX",
    "foreign_ratio": 0.0,
    "trust_ratio": 2.6302065552417897,
    "dealer_ratio": 0.0,
    "three_inst_ratio": 2.6302065552417897,
    "three_inst_ratio_change_20": 0.3244503395691978
  },
  {
    "date": "2025-11-27",
    "code": "6187",
    "name": "萬潤",
    "market": "TPEX",
    "foreign_ratio": 0.0,
    "trust_ratio": 2.6302065552417897,
    "dealer_ratio": 0.0,
    "three_inst_ratio": 2.6302065552417897,
    "three_inst_ratio_change_20": 0.3244503395691978
  },
  {
    "date": "2025-11-28",
    "code": "6187",
    "name": "萬潤",
    "market": "TPEX",
    "foreign_ratio": 0.0,
    "trust_ratio": 2.629174375116862,
    "dealer_ratio": 0.0,
    "three_inst_ratio": 2.629174375116862,
    "three_inst_ratio_change_20": 0.019957202715479738
  },
  {
    "date": "2025-12-01",
    "code": "6187",
    "name": "萬潤",
    "market": "TPEX",
    "foreign_ratio": 0.0,
    "trust_ratio": 2.6302065552417897,
    "dealer_ratio": 0.0,
    "three_inst_ratio": 2.6302065552417897,
    "three_inst_ratio_change_20": 0.02047329277794363
  },
  {
    "date": "2025-12-02",
    "code": "6187",
    "name": "萬潤",
    "market": "TPEX",
    "foreign_ratio": 0.0,
    "trust_ratio": 2.6322709154916457,
    "dealer_ratio": 0.0,
    "three_inst_ratio": 2.6322709154916457,
    "three_inst_ratio_change_20": 0.022537653027799642
  },
  {
    "date": "2025-12-03",
    "code": "6187",
    "name": "萬潤",
    "market": "TPEX",
    "foreign_ratio": 0.0,
    "trust_ratio": 2.6322709154916457,
    "dealer_ratio": 0.0,
    "three_inst_ratio": 2.6322709154916457,
    "three_inst_ratio_change_20": 0.02222799899032113
  },
  {
    "date": "2025-12-04",
    "code": "6187",
    "name": "萬潤",
    "market": "TPEX",
    "foreign_ratio": 0.0,
    "trust_ratio": 2.6322709154916457,
    "dealer_ratio": 0.0,
    "three_inst_ratio": 2.6322709154916457,
    "three_inst_ratio_change_20": 0.02222799899032113
  },
  {
    "date": "2025-12-05",
    "code": "6187",
    "name": "萬潤",
    "market": "TPEX",
    "foreign_ratio": 0.0,
    "trust_ratio": 2.6322709154916457,
    "dealer_ratio": 0.0,
    "three_inst_ratio": 2.6322709154916457,
    "three_inst_ratio_change_20": 0.017067098365681765
  },
  {
    "date": "2025-12-08",
    "code": "6187",
    "name": "萬潤",
    "market": "TPEX",
    "foreign_ratio": 0.0,
    "trust_ratio": 2.6322709154916457,
    "dealer_ratio": 0.0,
    "three_inst_ratio": 2.6322709154916457,
    "three_inst_ratio_change_20": 0.017067098365681765
  },
  {
    "date": "2025-12-09",
    "code": "6187",
    "name": "萬潤",
    "market": "TPEX",
    "foreign_ratio": 0.0,
    "trust_ratio": 2.6302065552417897,
    "dealer_ratio": 0.0,
    "three_inst_ratio": 2.6302065552417897,
    "three_inst_ratio_change_20": 0.015002738115825753
  },
  {
    "date": "2025-12-10",
    "code": "6187",
    "name": "萬潤",
    "market": "TPEX",
    "foreign_ratio": 0.0,
    "trust_ratio": 2.6302065552417897,
    "dealer_ratio": 0.0,
    "three_inst_ratio": 2.6302065552417897,
    "three_inst_ratio_change_20": 0.015002738115825753
  },
  {
    "date": "2025-12-11",
    "code": "6187",
    "name": "萬潤",
    "market": "TPEX",
    "foreign_ratio": 0.0,
    "trust_ratio": 2.628703700979895,
    "dealer_ratio": 0.0,
    "three_inst_ratio": 2.628703700979895,
    "three_inst_ratio_change_20": 0.01349988385393086
  },
  {
    "date": "2025-12-12",
    "code": "6187",
    "name": "萬潤",
    "market": "TPEX",
    "foreign_ratio": 0.0,
    "trust_ratio": 2.628703700979895,
    "dealer_ratio": 0.0,
    "three_inst_ratio": 2.628703700979895,
    "three_inst_ratio_change_20": 0.01349988385393086
  }
]