[
  {
    "code": "4967",
    "name": "十銓",
    "market": "TWSE",
    "three_inst_ratio": 22.20437436084159,
    "change": 8.357646042135281
  },
  {
    "code": "1727",
    "name": "中華化",
    "market": "TWSE",
    "three_inst_ratio": 9.56,
    "change": 4.65
  },
  {
    "code": "6770",
    "name": "力積電",
    "market": "TWSE",
    "three_inst_ratio": 18.142247858155816,
    "change": 3.483063998407319
  },
  {
    "code": "8131",
    "name": "福懋科",
    "market": "TWSE",
    "three_inst_ratio": 5.282587939570825,
    "change": 2.89
  },
  {
    "code": "00635U",
    "name": "期元大S&P黃金",
    "market": "TWSE",
    "three_inst_ratio": 16.77,
    "change": 2.289999999999999
  },
  {
    "code": "00715L",
    "name": "期街口布蘭特正2",
    "market": "TWSE",
    "three_inst_ratio": 3.59,
    "change": 2.2
  },
  {
    "code": "5521",
    "name": "工信",
    "market": "TWSE",
    "three_inst_ratio": 16.43,
    "change": 1.9399999999999995
  },
  {
    "code": "2337",
    "name": "旺宏",
    "market": "TWSE",
    "three_inst_ratio": 22.7950403040949,
    "change": 1.8913887475752347
  },
  {
    "code": "8422",
    "name": "可寧衛*",
    "market": "TWSE",
    "three_inst_ratio": 13.852497508238176,
    "change": 1.884115918594194
  },
  {
    "code": "2887",
    "name": "台新新光金",
    "market": "TWSE",
    "three_inst_ratio": 26.50291105068854,
    "change": 1.7488466497688435
  },
  {
    "code": "00738U",
    "name": "期元大道瓊白銀",
    "market": "TWSE",
    "three_inst_ratio": 5.39,
    "change": 1.7399999999999998
  },
  {
    "code": "00885",
    "name": "富邦越南",
    "market": "TWSE",
    "three_inst_ratio": 4.15,
    "change": 1.5800000000000005
  },
  {
    "code": "8103",
    "name": "瀚荃",
    "market": "TWSE",
    "three_inst_ratio": 19.225753260232064,
    "change": 1.5799999999999983
  },
  {
    "code": "6944",
    "name": "兆聯實業",
    "market": "TWSE",
    "three_inst_ratio": 14.383333428735785,
    "change": 1.5638463898926247
  },
  {
    "code": "00650L",
    "name": "復華香港正2",
    "market": "TWSE",
    "three_inst_ratio": 4.75,
    "change": 1.52
  },
  {
    "code": "8150",
    "name": "南茂",
    "market": "TWSE",
    "three_inst_ratio": 37.51268973595055,
    "change": 1.4270507710487834
  },
  {
    "code": "5522",
    "name": "遠雄",
    "market": "TWSE",
    "three_inst_ratio": 5.100561273669175,
    "change": 1.393293293141618
  },
  {
    "code": "3715",
    "name": "定穎投控",
    "market": "TWSE",
    "three_inst_ratio": 23.357866753552067,
    "change": 1.3185091659667378
  },
  {
    "code": "4764",
    "name": "雙鍵",
    "market": "TWSE",
    "three_inst_ratio": 26.05,
    "change": 1.3000000000000007
  },
  {
    "code": "00988A",
    "name": "主動統一全球創新",
    "market": "TWSE",
    "three_inst_ratio": 2.26,
    "change": 1.2699999999999998
  },
  {
    "code": "8110",
    "name": "華東",
    "market": "TWSE",
    "three_inst_ratio": 3.447408367826781,
    "change": 1.23
  },
  {
    "code": "3030",
    "name": "德律",
    "market": "TWSE",
    "three_inst_ratio": 13.250912893284113,
    "change": 1.1539905848884064
  },
  {
    "code": "2455",
    "name": "全新",
    "market": "TWSE",
    "three_inst_ratio": 41.336223806097976,
    "change": 1.0705306393708867
  },
  {
    "code": "00865B",
    "name": "國泰US短期公債",
    "market": "TWSE",
    "three_inst_ratio": 2.07,
    "change": 1.0199999999999998
  },
  {
    "code": "00945B",
    "name": "凱基美國非投等債",
    "market": "TWSE",
    "three_inst_ratio": 7.0565626649761795,
    "change": 0.9836795004306849
  },
  {
    "code": "6591",
    "name": "動力-KY",
    "market": "TWSE",
    "three_inst_ratio": 25.472406911891103,
    "change": 0.9499999999999993
  },
  {
    "code": "7769",
    "name": "鴻勁",
    "market": "TWSE",
    "three_inst_ratio": 13.53990107263936,
    "change": 0.920137275607182
  },
  {
    "code": "00735",
    "name": "國泰臺韓科技",
    "market": "TWSE",
    "three_inst_ratio": 5.09,
    "change": 0.8999999999999995
  },
  {
    "code": "2368",
    "name": "金像電",
    "market": "TWSE",
    "three_inst_ratio": 33.17249308684548,
    "change": 0.892278198250871
  },
  {
    "code": "6271",
    "name": "同欣電",
    "market": "TWSE",
    "three_inst_ratio": 26.35419919514785,
    "change": 0.8765615310704327
  },
  {
    "code": "00981A",
    "name": "主動統一台股增長",
    "market": "TWSE",
    "three_inst_ratio": 1.495885031985296,
    "change": 0.8720637222042822
  },
  {
    "code": "6831",
    "name": "邁科",
    "market": "TWSE",
    "three_inst_ratio": 6.760370370370371,
    "change": 0.858888888888889
  },
  {
    "code": "2303",
    "name": "聯電",
    "market": "TWSE",
    "three_inst_ratio": 29.451482078039877,
    "change": 0.8421565821845078
  },
  {
    "code": "2472",
    "name": "立隆電",
    "market": "TWSE",
    "three_inst_ratio": 13.54923739323445,
    "change": 0.8139618058532339
  },
  {
    "code": "3665",
    "name": "貿聯-KY",
    "market": "TWSE",
    "three_inst_ratio": 50.96372033901014,
    "change": 0.7906090712649458
  },
  {
    "code": "2548",
    "name": "華固",
    "market": "TWSE",
    "three_inst_ratio": 13.918848810928315,
    "change": 0.7725549903326439
  },
  {
    "code": "00753L",
    "name": "中信中國50正2",
    "market": "TWSE",
    "three_inst_ratio": 3.35,
    "change": 0.75
  },
  {
    "code": "00919",
    "name": "群益台灣精選高息",
    "market": "TWSE",
    "three_inst_ratio": 0.96,
    "change": 0.75
  },
  {
    "code": "00961",
    "name": "FT臺灣永續高息",
    "market": "TWSE",
    "three_inst_ratio": 2.51,
    "change": 0.7499999999999998
  },
  {
    "code": "1560",
    "name": "中砂",
    "market": "TWSE",
    "three_inst_ratio": 31.77574234702852,
    "change": 0.7441071967494253
  },
  {
    "code": "2329",
    "name": "華泰",
    "market": "TWSE",
    "three_inst_ratio": 12.935354607872293,
    "change": 0.7400000000000002
  },
  {
    "code": "5292",
    "name": "華懋",
    "market": "TWSE",
    "three_inst_ratio": 2.33,
    "change": 0.73
  },
  {
    "code": "2413",
    "name": "環科",
    "market": "TWSE",
    "three_inst_ratio": 3.08,
    "change": 0.73
  },
  {
    "code": "3006",
    "name": "晶豪科",
    "market": "TWSE",
    "three_inst_ratio": 18.18849022161262,
    "change": 0.7100000000000009
  },
  {
    "code": "4722",
    "name": "國精化",
    "market": "TWSE",
    "three_inst_ratio": 4.740813902478647,
    "change": 0.7080209611679038
  },
  {
    "code": "1216",
    "name": "統一",
    "market": "TWSE",
    "three_inst_ratio": 36.38371426715985,
    "change": 0.6916730112777998
  },
  {
    "code": "3060",
    "name": "銘異",
    "market": "TWSE",
    "three_inst_ratio": 8.2,
    "change": 0.6899999999999995
  },
  {
    "code": "3017",
    "name": "奇鋐",
    "market": "TWSE",
    "three_inst_ratio": 52.07030893711082,
    "change": 0.6890300872878825
  },
  {
    "code": "6155",
    "name": "鈞寶",
    "market": "TWSE",
    "three_inst_ratio": 7.24,
    "change": 0.6800000000000006
  },
  {
    "code": "3004",
    "name": "豐達科",
    "market": "TWSE",
    "three_inst_ratio": 2.6866320801874037,
    "change": 0.6799999999999997
  },
  {
    "code": "00953B",
    "name": "群益優選非投等債",
    "market": "TWSE",
    "three_inst_ratio": 3.1541146173421124,
    "change": 0.6769312102935952
  },
  {
    "code": "1513",
    "name": "中興電",
    "market": "TWSE",
    "three_inst_ratio": 17.49907850741896,
    "change": 0.6695292823316059
  },
  {
    "code": "2349",
    "name": "錸德",
    "market": "TWSE",
    "three_inst_ratio": 12.85,
    "change": 0.6600000000000001
  },
  {
    "code": "1319",
    "name": "東陽",
    "market": "TWSE",
    "three_inst_ratio": 14.0926928770804,
    "change": 0.6548534576829947
  },
  {
    "code": "1316",
    "name": "上曜",
    "market": "TWSE",
    "three_inst_ratio": 6.387941056607852,
    "change": 0.6475482786097722
  },
  {
    "code": "0052",
    "name": "富邦科技",
    "market": "TWSE",
    "three_inst_ratio": 1.7962759047324466,
    "change": 0.6414698339061398
  },
  {
    "code": "1587",
    "name": "吉茂",
    "market": "TWSE",
    "three_inst_ratio": 22.14,
    "change": 0.620000000000001
  },
  {
    "code": "8011",
    "name": "台通",
    "market": "TWSE",
    "three_inst_ratio": 5.13,
    "change": 0.6200000000000001
  },
  {
    "code": "2867",
    "name": "三商壽",
    "market": "TWSE",
    "three_inst_ratio": 12.020000305110548,
    "change": 0.5999999999999996
  },
  {
    "code": "2727",
    "name": "王品",
    "market": "TWSE",
    "three_inst_ratio": 23.265320679210973,
    "change": 0.5926028206450162
  },
  {
    "code": "6196",
    "name": "帆宣",
    "market": "TWSE",
    "three_inst_ratio": 12.869805986494464,
    "change": 0.590892799209989
  },
  {
    "code": "2375",
    "name": "凱美",
    "market": "TWSE",
    "three_inst_ratio": 8.76,
    "change": 0.5600000000000005
  },
  {
    "code": "6414",
    "name": "樺漢",
    "market": "TWSE",
    "three_inst_ratio": 28.734214811546803,
    "change": 0.5523768784755418
  },
  {
    "code": "4919",
    "name": "新唐",
    "market": "TWSE",
    "three_inst_ratio": 8.32002831087016,
    "change": 0.5500000000000007
  },
  {
    "code": "3321",
    "name": "同泰",
    "market": "TWSE",
    "three_inst_ratio": 0.98,
    "change": 0.55
  },
  {
    "code": "4927",
    "name": "泰鼎-KY",
    "market": "TWSE",
    "three_inst_ratio": 14.907971688076683,
    "change": 0.5300000000000011
  },
  {
    "code": "2605",
    "name": "新興",
    "market": "TWSE",
    "three_inst_ratio": 34.603066674005596,
    "change": 0.523066674005598
  },
  {
    "code": "3044",
    "name": "健鼎",
    "market": "TWSE",
    "three_inst_ratio": 43.35359606520245,
    "change": 0.514415993596792
  },
  {
    "code": "4763",
    "name": "材料*-KY",
    "market": "TWSE",
    "three_inst_ratio": 48.475252603741765,
    "change": 0.5085672454419665
  },
  {
    "code": "6282",
    "name": "康舒",
    "market": "TWSE",
    "three_inst_ratio": 10.325867704851747,
    "change": 0.4995198522517157
  },
  {
    "code": "00731",
    "name": "復華富時高息低波",
    "market": "TWSE",
    "three_inst_ratio": 2.305575447570332,
    "change": 0.49094490569841076
  },
  {
    "code": "2883",
    "name": "凱基金",
    "market": "TWSE",
    "three_inst_ratio": 26.940386512227782,
    "change": 0.48957966572526246
  },
  {
    "code": "0061",
    "name": "元大寶滬深",
    "market": "TWSE",
    "three_inst_ratio": 5.41,
    "change": 0.4800000000000004
  },
  {
    "code": "6805",
    "name": "富世達",
    "market": "TWSE",
    "three_inst_ratio": 29.313218020460866,
    "change": 0.46632131425469936
  },
  {
    "code": "6214",
    "name": "精誠",
    "market": "TWSE",
    "three_inst_ratio": 11.910346322723239,
    "change": 0.46438222606558455
  },
  {
    "code": "2637",
    "name": "慧洋-KY",
    "market": "TWSE",
    "three_inst_ratio": 11.169714896828328,
    "change": 0.4617038267236051
  },
  {
    "code": "6239",
    "name": "力成",
    "market": "TWSE",
    "three_inst_ratio": 36.924438437884184,
    "change": 0.45666722964090667
  },
  {
    "code": "5534",
    "name": "長虹",
    "market": "TWSE",
    "three_inst_ratio": 13.025658094095341,
    "change": 0.4400000000000013
  },
  {
    "code": "2478",
    "name": "大毅",
    "market": "TWSE",
    "three_inst_ratio": 10.14,
    "change": 0.4400000000000013
  },
  {
    "code": "2301",
    "name": "光寶科",
    "market": "TWSE",
    "three_inst_ratio": 30.414223833400833,
    "change": 0.4359406003722057
  },
  {
    "code": "3535",
    "name": "晶彩科",
    "market": "TWSE",
    "three_inst_ratio": 9.08,
    "change": 0.4299999999999997
  },
  {
    "code": "5871",
    "name": "中租-KY",
    "market": "TWSE",
    "three_inst_ratio": 38.857501781590976,
    "change": 0.426741010350284
  },
  {
    "code": "3048",
    "name": "益登",
    "market": "TWSE",
    "three_inst_ratio": 2.33,
    "change": 0.42000000000000015
  },
  {
    "code": "3032",
    "name": "偉訓",
    "market": "TWSE",
    "three_inst_ratio": 6.368474046301338,
    "change": 0.41999999999999993
  },
  {
    "code": "6235",
    "name": "華孚",
    "market": "TWSE",
    "three_inst_ratio": 5.315615063288699,
    "change": 0.40799906262086605
  },
  {
    "code": "3033",
    "name": "威健",
    "market": "TWSE",
    "three_inst_ratio": 8.110895801496284,
    "change": 0.396970090147966
  },
  {
    "code": "2603",
    "name": "長榮",
    "market": "TWSE",
    "three_inst_ratio": 17.63485468191598,
    "change": 0.39363634407932935
  },
  {
    "code": "6133",
    "name": "金橋",
    "market": "TWSE",
    "three_inst_ratio": 4.06,
    "change": 0.3899999999999997
  },
  {
    "code": "3010",
    "name": "華立",
    "market": "TWSE",
    "three_inst_ratio": 14.528071755598203,
    "change": 0.3840931877066627
  },
  {
    "code": "00665L",
    "name": "富邦恒生國企正2",
    "market": "TWSE",
    "three_inst_ratio": 1.6,
    "change": 0.3700000000000001
  },
  {
    "code": "00717",
    "name": "富邦美國特別股",
    "market": "TWSE",
    "three_inst_ratio": 2.39,
    "change": 0.3700000000000001
  },
  {
    "code": "3708",
    "name": "上緯投控",
    "market": "TWSE",
    "three_inst_ratio": 5.861604642844502,
    "change": 0.3690678209566318
  },
  {
    "code": "4557",
    "name": "永新-KY",
    "market": "TWSE",
    "three_inst_ratio": 33.58,
    "change": 0.3500000000000014
  },
  {
    "code": "3052",
    "name": "夆典",
    "market": "TWSE",
    "three_inst_ratio": 4.38,
    "change": 0.34999999999999964
  },
  {
    "code": "1409",
    "name": "新纖",
    "market": "TWSE",
    "three_inst_ratio": 11.929206571000854,
    "change": 0.33999999999999986
  },
  {
    "code": "00939",
    "name": "統一台灣高息動能",
    "market": "TWSE",
    "three_inst_ratio": 0.62,
    "change": 0.33
  },
  {
    "code": "4737",
    "name": "華廣",
    "market": "TWSE",
    "three_inst_ratio": 23.9,
    "change": 0.3299999999999983
  },
  {
    "code": "8478",
    "name": "東哥遊艇",
    "market": "TWSE",
    "three_inst_ratio": 40.74300852476958,
    "change": 0.3199999999999932
  },
  {
    "code": "1717",
    "name": "長興",
    "market": "TWSE",
    "three_inst_ratio": 13.089467168439496,
    "change": 0.312388578195101
  },
  {
    "code": "7610",
    "name": "聯友金屬-創",
    "market": "TWSE",
    "three_inst_ratio": 15.63,
    "change": 0.3100000000000005
  },
  {
    "code": "3057",
    "name": "喬鼎",
    "market": "TWSE",
    "three_inst_ratio": 2.3,
    "change": 0.30999999999999983
  },
  {
    "code": "2312",
    "name": "金寶",
    "market": "TWSE",
    "three_inst_ratio": 9.8463675982922,
    "change": 0.30402784243372594
  },
  {
    "code": "8210",
    "name": "勤誠",
    "market": "TWSE",
    "three_inst_ratio": 21.91308041892006,
    "change": 0.30014568764359595
  },
  {
    "code": "6438",
    "name": "迅得",
    "market": "TWSE",
    "three_inst_ratio": 7.778332245116176,
    "change": 0.2999999999999998
  },
  {
    "code": "00983D",
    "name": "主動富邦複合收益",
    "market": "TWSE",
    "three_inst_ratio": 4.0,
    "change": 0.2999999999999998
  },
  {
    "code": "3673",
    "name": "TPK-KY",
    "market": "TWSE",
    "three_inst_ratio": 41.27926228980734,
    "change": 0.28999999999999915
  },
  {
    "code": "2542",
    "name": "興富發",
    "market": "TWSE",
    "three_inst_ratio": 9.172841686750267,
    "change": 0.2820117702525202
  },
  {
    "code": "3645",
    "name": "達邁",
    "market": "TWSE",
    "three_inst_ratio": 9.15,
    "change": 0.28000000000000114
  },
  {
    "code": "00900",
    "name": "富邦特選高股息30",
    "market": "TWSE",
    "three_inst_ratio": 0.9450655292603415,
    "change": 0.2719358228398414
  },
  {
    "code": "00898",
    "name": "國泰基因免疫革命",
    "market": "TWSE",
    "three_inst_ratio": 1.12,
    "change": 0.27000000000000013
  },
  {
    "code": "2489",
    "name": "瑞軒",
    "market": "TWSE",
    "three_inst_ratio": 11.24,
    "change": 0.2699999999999996
  },
  {
    "code": "2884",
    "name": "玉山金",
    "market": "TWSE",
    "three_inst_ratio": 33.93045531717571,
    "change": 0.2666130703598384
  },
  {
    "code": "1449",
    "name": "佳和",
    "market": "TWSE",
    "three_inst_ratio": 6.48,
    "change": 0.2600000000000007
  },
  {
    "code": "00918",
    "name": "大華優利高填息30",
    "market": "TWSE",
    "three_inst_ratio": 0.4,
    "change": 0.26
  },
  {
    "code": "1504",
    "name": "東元",
    "market": "TWSE",
    "three_inst_ratio": 10.33680953002907,
    "change": 0.25581262391820125
  },
  {
    "code": "6830",
    "name": "汎銓",
    "market": "TWSE",
    "three_inst_ratio": 3.1838060864033313,
    "change": 0.25
  },
  {
    "code": "2374",
    "name": "佳能",
    "market": "TWSE",
    "three_inst_ratio": 5.988989619058475,
    "change": 0.247850536844763
  },
  {
    "code": "2753",
    "name": "八方雲集",
    "market": "TWSE",
    "three_inst_ratio": 12.57310927983034,
    "change": 0.24699901549702297
  },
  {
    "code": "2491",
    "name": "吉祥全",
    "market": "TWSE",
    "three_inst_ratio": 5.74,
    "change": 0.2400000000000002
  },
  {
    "code": "6192",
    "name": "巨路",
    "market": "TWSE",
    "three_inst_ratio": 20.81,
    "change": 0.23999999999999844
  },
  {
    "code": "1708",
    "name": "東鹼",
    "market": "TWSE",
    "three_inst_ratio": 9.577349149945997,
    "change": 0.23999999999999844
  },
  {
    "code": "2812",
    "name": "台中銀",
    "market": "TWSE",
    "three_inst_ratio": 11.147415209834653,
    "change": 0.2392715256547735
  },
  {
    "code": "3406",
    "name": "玉晶光",
    "market": "TWSE",
    "three_inst_ratio": 32.15070112570917,
    "change": 0.2322881662351115
  },
  {
    "code": "1314",
    "name": "中石化",
    "market": "TWSE",
    "three_inst_ratio": 9.550005204961709,
    "change": 0.23000000000000043
  },
  {
    "code": "6112",
    "name": "邁達特",
    "market": "TWSE",
    "three_inst_ratio": 1.51,
    "change": 0.22999999999999998
  },
  {
    "code": "8072",
    "name": "陞泰",
    "market": "TWSE",
    "three_inst_ratio": 3.35,
    "change": 0.22999999999999998
  },
  {
    "code": "2880",
    "name": "華南金",
    "market": "TWSE",
    "three_inst_ratio": 18.17636103717972,
    "change": 0.2287219275225425
  },
  {
    "code": "9945",
    "name": "潤泰新",
    "market": "TWSE",
    "three_inst_ratio": 9.382703037624498,
    "change": 0.22689115643360047
  },
  {
    "code": "5222",
    "name": "全訊",
    "market": "TWSE",
    "three_inst_ratio": 6.033023968842011,
    "change": 0.22559796030610446
  },
  {
    "code": "2630",
    "name": "亞航",
    "market": "TWSE",
    "three_inst_ratio": 4.24,
    "change": 0.22000000000000064
  },
  {
    "code": "1307",
    "name": "三芳",
    "market": "TWSE",
    "three_inst_ratio": 7.510878603505362,
    "change": 0.21999999999999975
  },
  {
    "code": "6862",
    "name": "三集瑞-KY",
    "market": "TWSE",
    "three_inst_ratio": 64.61,
    "change": 0.21999999999999886
  },
  {
    "code": "2476",
    "name": "鉅祥",
    "market": "TWSE",
    "three_inst_ratio": 9.04,
    "change": 0.21999999999999886
  },
  {
    "code": "6197",
    "name": "佳必琪",
    "market": "TWSE",
    "three_inst_ratio": 5.875718637966674,
    "change": 0.21860300816764422
  },
  {
    "code": "00636",
    "name": "國泰中國A50",
    "market": "TWSE",
    "three_inst_ratio": 0.9457641459545214,
    "change": 0.21254721837839896
  },
  {
    "code": "00651R",
    "name": "復華香港反1",
    "market": "TWSE",
    "three_inst_ratio": 2.35,
    "change": 0.20999999999999996
  },
  {
    "code": "2836",
    "name": "高雄銀",
    "market": "TWSE",
    "three_inst_ratio": 8.0501087005564,
    "change": 0.20999999999999996
  },
  {
    "code": "2458",
    "name": "義隆",
    "market": "TWSE",
    "three_inst_ratio": 17.325404069901293,
    "change": 0.2014061335026831
  },
  {
    "code": "3622",
    "name": "洋華",
    "market": "TWSE",
    "three_inst_ratio": 4.84,
    "change": 0.20000000000000018
  },
  {
    "code": "3533",
    "name": "嘉澤",
    "market": "TWSE",
    "three_inst_ratio": 36.89552246684536,
    "change": 0.19516207362225657
  },
  {
    "code": "6605",
    "name": "帝寶",
    "market": "TWSE",
    "three_inst_ratio": 14.975491012568556,
    "change": 0.19386525971855306
  },
  {
    "code": "2834",
    "name": "臺企銀",
    "market": "TWSE",
    "three_inst_ratio": 19.846933332296803,
    "change": 0.19271994564458694
  },
  {
    "code": "2428",
    "name": "興勤",
    "market": "TWSE",
    "three_inst_ratio": 16.132013026559125,
    "change": 0.19170843870733023
  },
  {
    "code": "00655L",
    "name": "國泰中國A50正2",
    "market": "TWSE",
    "three_inst_ratio": 1.21,
    "change": 0.18999999999999995
  },
  {
    "code": "3138",
    "name": "耀登",
    "market": "TWSE",
    "three_inst_ratio": 2.44,
    "change": 0.18999999999999995
  },
  {
    "code": "2323",
    "name": "中環",
    "market": "TWSE",
    "three_inst_ratio": 10.72231104392901,
    "change": 0.1899999999999995
  },
  {
    "code": "5225",
    "name": "東科-KY",
    "market": "TWSE",
    "three_inst_ratio": 41.65570669030007,
    "change": 0.18999999999999773
  },
  {
    "code": "00752",
    "name": "中信中國50",
    "market": "TWSE",
    "three_inst_ratio": 1.6739509862522417,
    "change": 0.1882231541126269
  },
  {
    "code": "2492",
    "name": "華新科",
    "market": "TWSE",
    "three_inst_ratio": 10.839592826644392,
    "change": 0.1822642840475659
  },
  {
    "code": "1536",
    "name": "和大",
    "market": "TWSE",
    "three_inst_ratio": 7.65,
    "change": 0.1800000000000006
  },
  {
    "code": "2427",
    "name": "三商電",
    "market": "TWSE",
    "three_inst_ratio": 3.3406679415389067,
    "change": 0.18000000000000016
  },
  {
    "code": "1809",
    "name": "中釉",
    "market": "TWSE",
    "three_inst_ratio": 4.12,
    "change": 0.18000000000000016
  },
  {
    "code": "00714",
    "name": "群益道瓊美國地產",
    "market": "TWSE",
    "three_inst_ratio": 2.3,
    "change": 0.17999999999999972
  },
  {
    "code": "4949",
    "name": "有成精密",
    "market": "TWSE",
    "three_inst_ratio": 5.81,
    "change": 0.17999999999999972
  },
  {
    "code": "3046",
    "name": "建碁",
    "market": "TWSE",
    "three_inst_ratio": 4.2631653818943755,
    "change": 0.17999999999999972
  },
  {
    "code": "2845",
    "name": "遠東銀",
    "market": "TWSE",
    "three_inst_ratio": 10.160349932555674,
    "change": 0.17556038316475586
  },
  {
    "code": "2606",
    "name": "裕民",
    "market": "TWSE",
    "three_inst_ratio": 10.923734860027785,
    "change": 0.17006001706074514
  },
  {
    "code": "2369",
    "name": "菱生",
    "market": "TWSE",
    "three_inst_ratio": 15.31,
    "change": 0.16999999999999993
  },
  {
    "code": "4142",
    "name": "國光生",
    "market": "TWSE",
    "three_inst_ratio": 5.78,
    "change": 0.16999999999999993
  },
  {
    "code": "2636",
    "name": "台驊控股",
    "market": "TWSE",
    "three_inst_ratio": 8.118317908040195,
    "change": 0.16999999999999904
  },
  {
    "code": "00693U",
    "name": "期街口S&P黃豆",
    "market": "TWSE",
    "three_inst_ratio": 1.33,
    "change": 0.16000000000000014
  },
  {
    "code": "6994",
    "name": "富威電力",
    "market": "TWSE",
    "three_inst_ratio": 2.17,
    "change": 0.16000000000000014
  },
  {
    "code": "2468",
    "name": "華經",
    "market": "TWSE",
    "three_inst_ratio": 3.98,
    "change": 0.16000000000000014
  },
  {
    "code": "6695",
    "name": "芯鼎",
    "market": "TWSE",
    "three_inst_ratio": 1.57,
    "change": 0.16000000000000014
  },
  {
    "code": "3311",
    "name": "閎暉",
    "market": "TWSE",
    "three_inst_ratio": 1.76,
    "change": 0.15999999999999992
  },
  {
    "code": "3532",
    "name": "台勝科",
    "market": "TWSE",
    "three_inst_ratio": 47.791613991862285,
    "change": 0.15980946158588694
  },
  {
    "code": "2892",
    "name": "第一金",
    "market": "TWSE",
    "three_inst_ratio": 23.36746454188347,
    "change": 0.15872769627686978
  },
  {
    "code": "2495",
    "name": "普安",
    "market": "TWSE",
    "three_inst_ratio": 4.483317557366466,
    "change": 0.15817219086518186
  },
  {
    "code": "4562",
    "name": "穎漢",
    "market": "TWSE",
    "three_inst_ratio": 2.16,
    "change": 0.15000000000000036
  },
  {
    "code": "3312",
    "name": "弘憶股",
    "market": "TWSE",
    "three_inst_ratio": 1.98,
    "change": 0.1499999999999999
  },
  {
    "code": "2241",
    "name": "艾姆勒",
    "market": "TWSE",
    "three_inst_ratio": 11.54,
    "change": 0.14999999999999858
  },
  {
    "code": "5243",
    "name": "乙盛-KY",
    "market": "TWSE",
    "three_inst_ratio": 58.61771581422689,
    "change": 0.14966849931953163
  },
  {
    "code": "2501",
    "name": "國建",
    "market": "TWSE",
    "three_inst_ratio": 9.309999272509202,
    "change": 0.14853392800076826
  },
  {
    "code": "5880",
    "name": "合庫金",
    "market": "TWSE",
    "three_inst_ratio": 16.419311192579933,
    "change": 0.14641236360375132
  },
  {
    "code": "6937",
    "name": "天虹",
    "market": "TWSE",
    "three_inst_ratio": 2.312954682770783,
    "change": 0.1411211426414627
  },
  {
    "code": "5519",
    "name": "隆大",
    "market": "TWSE",
    "three_inst_ratio": 4.12,
    "change": 0.14000000000000012
  },
  {
    "code": "3338",
    "name": "泰碩",
    "market": "TWSE",
    "three_inst_ratio": 2.5392406190229866,
    "change": 0.13999999999999968
  },
  {
    "code": "1325",
    "name": "恆大",
    "market": "TWSE",
    "three_inst_ratio": 2.84,
    "change": 0.13999999999999968
  },
  {
    "code": "1702",
    "name": "南僑",
    "market": "TWSE",
    "three_inst_ratio": 9.202166004026438,
    "change": 0.13635130999020895
  },
  {
    "code": "8112",
    "name": "至上",
    "market": "TWSE",
    "three_inst_ratio": 17.532797396771347,
    "change": 0.13387806810531444
  },
  {
    "code": "8454",
    "name": "富邦媒",
    "market": "TWSE",
    "three_inst_ratio": 13.528270006512871,
    "change": 0.13075478740421964
  },
  {
    "code": "6834",
    "name": "天二科技",
    "market": "TWSE",
    "three_inst_ratio": 10.63,
    "change": 0.13000000000000078
  },
  {
    "code": "00946",
    "name": "群益科技高息成長",
    "market": "TWSE",
    "three_inst_ratio": 0.42,
    "change": 0.13
  },
  {
    "code": "1711",
    "name": "永光",
    "market": "TWSE",
    "three_inst_ratio": 4.33,
    "change": 0.1299999999999999
  },
  {
    "code": "6756",
    "name": "威鋒電子",
    "market": "TWSE",
    "three_inst_ratio": 3.0543127039560316,
    "change": 0.1299999999999999
  },
  {
    "code": "00666R",
    "name": "富邦恒生國企反1",
    "market": "TWSE",
    "three_inst_ratio": 5.3,
    "change": 0.1299999999999999
  },
  {
    "code": "6215",
    "name": "和椿",
    "market": "TWSE",
    "three_inst_ratio": 5.87,
    "change": 0.1299999999999999
  },
  {
    "code": "7749",
    "name": "意騰-KY",
    "market": "TWSE",
    "three_inst_ratio": 23.584419166243887,
    "change": 0.129999999999999
  },
  {
    "code": "6456",
    "name": "GIS-KY",
    "market": "TWSE",
    "three_inst_ratio": 49.73,
    "change": 0.12999999999999545
  },
  {
    "code": "3026",
    "name": "禾伸堂",
    "market": "TWSE",
    "three_inst_ratio": 14.906828463491161,
    "change": 0.12921634968473583
  },
  {
    "code": "4961",
    "name": "天鈺",
    "market": "TWSE",
    "three_inst_ratio": 15.847775039394087,
    "change": 0.12706023886151918
  },
  {
    "code": "2801",
    "name": "彰銀",
    "market": "TWSE",
    "three_inst_ratio": 19.18875965747999,
    "change": 0.12395132518947705
  },
  {
    "code": "2367",
    "name": "燿華",
    "market": "TWSE",
    "three_inst_ratio": 8.91,
    "change": 0.120000000000001
  },
  {
    "code": "00902",
    "name": "中信電池及儲能",
    "market": "TWSE",
    "three_inst_ratio": 0.67,
    "change": 0.12
  },
  {
    "code": "2528",
    "name": "皇普",
    "market": "TWSE",
    "three_inst_ratio": 3.09,
    "change": 0.11999999999999966
  },
  {
    "code": "6672",
    "name": "騰輝電子-KY",
    "market": "TWSE",
    "three_inst_ratio": 23.97,
    "change": 0.11999999999999744
  },
  {
    "code": "00662",
    "name": "富邦NASDAQ",
    "market": "TWSE",
    "three_inst_ratio": 0.7451554396919589,
    "change": 0.11929226619118449
  },
  {
    "code": "2881",
    "name": "富邦金",
    "market": "TWSE",
    "three_inst_ratio": 17.966257386063713,
    "change": 0.11409950656934953
  },
  {
    "code": "00929",
    "name": "復華台灣科技優息",
    "market": "TWSE",
    "three_inst_ratio": 0.58,
    "change": 0.10999999999999999
  },
  {
    "code": "0055",
    "name": "元大MSCI金融",
    "market": "TWSE",
    "three_inst_ratio": 0.59,
    "change": 0.10999999999999999
  }
]